pynotifier/__init__.py
pynotifier/client.py
pynotifier/notification.py
pynotifier/utils.py
pynotifier/backends/__init__.py
pynotifier/backends/backend.py
pynotifier/backends/smtp.py
pynotifier/backends/platform/__init__.py
pynotifier/backends/platform/darwin.py
pynotifier/backends/platform/linux.py
pynotifier/backends/platform/windows.py
py_notifier-0.5.0.dist-info/LICENSE
py_notifier-0.5.0.dist-info/METADATA
py_notifier-0.5.0.dist-info/WHEEL
py_notifier-0.5.0.dist-info/top_level.txt
py_notifier-0.5.0.dist-info/RECORD
